odoo/addons/sale_blanket_order_stock_terms/LICENSE
odoo/addons/sale_blanket_order_stock_terms/README.rst
odoo/addons/sale_blanket_order_stock_terms/__init__.py
odoo/addons/sale_blanket_order_stock_terms/__manifest__.py
odoo/addons/sale_blanket_order_stock_terms/i18n/de.po
odoo/addons/sale_blanket_order_stock_terms/images/screen.png
odoo/addons/sale_blanket_order_stock_terms/models/__init__.py
odoo/addons/sale_blanket_order_stock_terms/models/blanket_order.py
odoo/addons/sale_blanket_order_stock_terms/models/sale_order.py
odoo/addons/sale_blanket_order_stock_terms/static/description/icon.png
odoo/addons/sale_blanket_order_stock_terms/static/description/index.html
odoo/addons/sale_blanket_order_stock_terms/tests/TEST_INSTRUCTIONS.rst
odoo/addons/sale_blanket_order_stock_terms/views/sale_blanket_order.xml
odoo_addon_sale_blanket_order_stock_terms-16.0.1.0.0.dist-info/METADATA
odoo_addon_sale_blanket_order_stock_terms-16.0.1.0.0.dist-info/WHEEL
odoo_addon_sale_blanket_order_stock_terms-16.0.1.0.0.dist-info/top_level.txt
odoo_addon_sale_blanket_order_stock_terms-16.0.1.0.0.dist-info/RECORD
